<annotation>
	<folder>fire_data1024</folder>
	<filename>421.jpg</filename>
	<path>G:\coco128\fire_data1024\421.jpg</path>
	<source>
		<database>Unknown</database>
	</source>
	<size>
		<width>500</width>
		<height>679</height>
		<depth>3</depth>
	</size>
	<segmented>0</segmented>
	<object>
		<name>fire</name>
		<pose>Unspecified</pose>
		<truncated>0</truncated>
		<difficult>0</difficult>
		<bndbox>
			<xmin>176</xmin>
			<ymin>311</ymin>
			<xmax>341</xmax>
			<ymax>526</ymax>
		</bndbox>
	</object>
</annotation>
