<annotation verified="yes">
	<folder>fire_data1024</folder>
	<filename>562.jpg</filename>
	<path>G:\coco128\fire_data1024\562.jpg</path>
	<source>
		<database>Unknown</database>
	</source>
	<size>
		<width>6000</width>
		<height>3376</height>
		<depth>3</depth>
	</size>
	<segmented>0</segmented>
	<object>
		<name>fire</name>
		<pose>Unspecified</pose>
		<truncated>0</truncated>
		<difficult>0</difficult>
		<bndbox>
			<xmin>1794</xmin>
			<ymin>162</ymin>
			<xmax>4094</xmax>
			<ymax>2646</ymax>
		</bndbox>
	</object>
</annotation>
