<annotation>
	<folder>2</folder>
	<filename>620.jpg</filename>
	<path>C:\Users\82686\Pictures\apples_datas\train\数据集\2\620.jpg</path>
	<source>
		<database>Unknown</database>
	</source>
	<size>
		<width>275</width>
		<height>256</height>
		<depth>3</depth>
	</size>
	<segmented>0</segmented>
	<object>
		<name>Apple_Scab</name>
		<pose>Unspecified</pose>
		<truncated>0</truncated>
		<difficult>0</difficult>
		<bndbox>
			<xmin>123</xmin>
			<ymin>121</ymin>
			<xmax>142</xmax>
			<ymax>138</ymax>
		</bndbox>
	</object>
	<object>
		<name>Apple_Scab</name>
		<pose>Unspecified</pose>
		<truncated>0</truncated>
		<difficult>0</difficult>
		<bndbox>
			<xmin>144</xmin>
			<ymin>139</ymin>
			<xmax>163</xmax>
			<ymax>159</ymax>
		</bndbox>
	</object>
	<object>
		<name>Apple_Scab</name>
		<pose>Unspecified</pose>
		<truncated>0</truncated>
		<difficult>0</difficult>
		<bndbox>
			<xmin>108</xmin>
			<ymin>143</ymin>
			<xmax>131</xmax>
			<ymax>163</ymax>
		</bndbox>
	</object>
	<object>
		<name>Apple_Scab</name>
		<pose>Unspecified</pose>
		<truncated>0</truncated>
		<difficult>0</difficult>
		<bndbox>
			<xmin>82</xmin>
			<ymin>116</ymin>
			<xmax>95</xmax>
			<ymax>132</ymax>
		</bndbox>
	</object>
</annotation>
