<annotation>
	<folder>images</folder>
	<filename>775.jpg</filename>
	<path>D:\临时文件夹\数据集\5\images\775.jpg</path>
	<source>
		<database>Unknown</database>
	</source>
	<size>
		<width>256</width>
		<height>278</height>
		<depth>3</depth>
	</size>
	<segmented>0</segmented>
	<object>
		<name>Cedar_Apple_Rust</name>
		<pose>Unspecified</pose>
		<truncated>0</truncated>
		<difficult>0</difficult>
		<bndbox>
			<xmin>113</xmin>
			<ymin>81</ymin>
			<xmax>123</xmax>
			<ymax>98</ymax>
		</bndbox>
	</object>
	<object>
		<name>Cedar_Apple_Rust</name>
		<pose>Unspecified</pose>
		<truncated>0</truncated>
		<difficult>0</difficult>
		<bndbox>
			<xmin>93</xmin>
			<ymin>124</ymin>
			<xmax>120</xmax>
			<ymax>149</ymax>
		</bndbox>
	</object>
	<object>
		<name>Cedar_Apple_Rust</name>
		<pose>Unspecified</pose>
		<truncated>0</truncated>
		<difficult>0</difficult>
		<bndbox>
			<xmin>120</xmin>
			<ymin>128</ymin>
			<xmax>130</xmax>
			<ymax>156</ymax>
		</bndbox>
	</object>
	<object>
		<name>Cedar_Apple_Rust</name>
		<pose>Unspecified</pose>
		<truncated>0</truncated>
		<difficult>0</difficult>
		<bndbox>
			<xmin>74</xmin>
			<ymin>172</ymin>
			<xmax>90</xmax>
			<ymax>191</ymax>
		</bndbox>
	</object>
</annotation>
